esi_client/__init__.py
esi_client/api_client.py
esi_client/configuration.py
esi_client/exceptions.py
esi_client/model_utils.py
esi_client/rest.py
esi_client/api/__init__.py
esi_client/api/alliance_api.py
esi_client/api/assets_api.py
esi_client/api/bookmarks_api.py
esi_client/api/calendar_api.py
esi_client/api/character_api.py
esi_client/api/clones_api.py
esi_client/api/contacts_api.py
esi_client/api/contracts_api.py
esi_client/api/corporation_api.py
esi_client/api/dogma_api.py
esi_client/api/faction_warfare_api.py
esi_client/api/fittings_api.py
esi_client/api/fleets_api.py
esi_client/api/incursions_api.py
esi_client/api/industry_api.py
esi_client/api/insurance_api.py
esi_client/api/killmails_api.py
esi_client/api/location_api.py
esi_client/api/loyalty_api.py
esi_client/api/mail_api.py
esi_client/api/market_api.py
esi_client/api/opportunities_api.py
esi_client/api/planetary_interaction_api.py
esi_client/api/routes_api.py
esi_client/api/search_api.py
esi_client/api/skills_api.py
esi_client/api/sovereignty_api.py
esi_client/api/status_api.py
esi_client/api/universe_api.py
esi_client/api/user_interface_api.py
esi_client/api/wallet_api.py
esi_client/api/wars_api.py
esi_client/apis/__init__.py
esi_client/docs/AllianceApi.md
esi_client/docs/AssetsApi.md
esi_client/docs/BadRequest.md
esi_client/docs/BookmarksApi.md
esi_client/docs/CalendarApi.md
esi_client/docs/CharacterApi.md
esi_client/docs/ClonesApi.md
esi_client/docs/ContactsApi.md
esi_client/docs/ContractsApi.md
esi_client/docs/CorporationApi.md
esi_client/docs/DeleteCharactersCharacterIdMailLabelsLabelIdUnprocessableEntity.md
esi_client/docs/DeleteFleetsFleetIdMembersMemberIdNotFound.md
esi_client/docs/DeleteFleetsFleetIdSquadsSquadIdNotFound.md
esi_client/docs/DeleteFleetsFleetIdWingsWingIdNotFound.md
esi_client/docs/DogmaApi.md
esi_client/docs/ErrorLimited.md
esi_client/docs/FactionWarfareApi.md
esi_client/docs/FittingsApi.md
esi_client/docs/FleetsApi.md
esi_client/docs/Forbidden.md
esi_client-0.1.0.dist-info/METADATA
esi_client-0.1.0.dist-info/WHEEL
esi_client-0.1.0.dist-info/licenses/LICENSE
esi_client-0.1.0.dist-info/RECORD
