Metadata-Version: 2.3
Name: esi-client
Version: 0.1.0
Summary: A Python client for accessing the complete Eve Online ESI API.
Project-URL: Homepage, https://gitlab.com/ErikKalkoken/esi-client-generator
Maintainer-email: Erik Kalkoken <kalkoken87@gmail.com>
License: MIT License
Keywords: EVE Swagger Interface,Eve Online
Classifier: Environment :: Web Environment
Classifier: Intended Audience :: Developers
Classifier: License :: OSI Approved :: MIT License
Classifier: Operating System :: OS Independent
Classifier: Programming Language :: Python
Classifier: Programming Language :: Python :: 3
Classifier: Programming Language :: Python :: 3.7
Classifier: Programming Language :: Python :: 3.8
Classifier: Programming Language :: Python :: 3.9
Classifier: Programming Language :: Python :: 3.10
Classifier: Programming Language :: Python :: 3.11
Classifier: Topic :: Internet :: WWW/HTTP
Classifier: Topic :: Internet :: WWW/HTTP :: Dynamic Content
Requires-Python: >=3.6
Requires-Dist: certifi>=2017.4.17
Requires-Dist: python-dateutil>=2.1
Requires-Dist: six>=1.10
Requires-Dist: urllib3>=1.23
